stlcontainers/__init__.py
stlcontainers/priority_queue.py
stlcontainers-0.0.2.dist-info/METADATA
stlcontainers-0.0.2.dist-info/WHEEL
stlcontainers-0.0.2.dist-info/licenses/LICENSE
stlcontainers-0.0.2.dist-info/RECORD
