Metadata-Version: 2.3
Name: stlcontainers
Version: 0.0.2
Summary: CPP styled containers for python.
Project-URL: Homepage, https://github.com/lbyxiafei/priority_queue
Author-email: Binyan Li <lbyxiafei@gmail.com>
License-File: LICENSE
Classifier: License :: OSI Approved :: MIT License
Classifier: Operating System :: OS Independent
Classifier: Programming Language :: Python :: 3
Requires-Python: >=3.8
